dbackup/__init__.py
dbackup/admin.py
dbackup/apps.py
dbackup/models.py
dbackup/tests.py
dbackup/views.py
dbackup/management/commands/dumpdatautf8.py
dbackup/migrations/__init__.py
dbackup-1.0.1.dist-info/LICENSE
dbackup-1.0.1.dist-info/METADATA
dbackup-1.0.1.dist-info/WHEEL
dbackup-1.0.1.dist-info/top_level.txt
dbackup-1.0.1.dist-info/RECORD
